git_import_contributions/Committer.py
git_import_contributions/Content.py
git_import_contributions/ImporterFromRepository.py
git_import_contributions/ImporterFromStats.py
git_import_contributions/README.md
git_import_contributions/Stats.py
git_import_contributions/__init__.py
git_import_contributions/cli.py
git_import_contributions/commons.py
git_import_contributions/generators/BashGenerator.py
git_import_contributions/generators/CGenerator.py
git_import_contributions/generators/CppGenerator.py
git_import_contributions/generators/CssGenerator.py
git_import_contributions/generators/Generator.py
git_import_contributions/generators/HtmlGenerator.py
git_import_contributions/generators/JavaGenerator.py
git_import_contributions/generators/JsGenerator.py
git_import_contributions/generators/JsonGenerator.py
git_import_contributions/generators/KotlinGenerator.py
git_import_contributions/generators/LuaGenerator.py
git_import_contributions/generators/PhpGenerator.py
git_import_contributions/generators/PyGenerator.py
git_import_contributions/generators/RubyGenerator.py
git_import_contributions/generators/ScalaGenerator.py
git_import_contributions/generators/SqlGenerator.py
git_import_contributions/generators/SwiftGenerator.py
git_import_contributions/generators/TerraformGenerator.py
git_import_contributions/generators/TsGenerator.py
git_import_contributions/generators/__init__.py
git_import_contributions-2.0.2.dist-info/LICENSE
git_import_contributions-2.0.2.dist-info/METADATA
git_import_contributions-2.0.2.dist-info/WHEEL
git_import_contributions-2.0.2.dist-info/entry_points.txt
git_import_contributions-2.0.2.dist-info/top_level.txt
git_import_contributions-2.0.2.dist-info/RECORD
