Metadata-Version: 2.2
Name: git-import-contributions
Version: 2.0.2
Summary: This tool helps users to import contributions to GitHub from private git repositories, or from public repositories that are not hosted in GitHub
Home-page: https://github.com/miromannino/Contributions-Importer-For-Github
Author: Miro Mannino
Requires-Python: >=3.10
License-File: LICENSE
Requires-Dist: gitpython
Dynamic: author
Dynamic: description
Dynamic: description-content-type
Dynamic: home-page
Dynamic: requires-dist
Dynamic: requires-python
Dynamic: summary
